longtasks/__init__.py
longtasks/init.py
longtasks/longtasks.py
longtasks-0.1.0.dist-info/METADATA
longtasks-0.1.0.dist-info/WHEEL
longtasks-0.1.0.dist-info/top_level.txt
longtasks-0.1.0.dist-info/RECORD
