Metadata-Version: 2.4
Name: longtasks
Version: 0.1.0
Summary: long task engine with submit, get_status interface to client
Author-email: Yu Moqing <yumoqing@gmail.com>
License: MIT
Requires-Dist: ahserver
Requires-Dist: sqlor
Requires-Dist: appPublic
Requires-Dist: aioredis
